dapr_httpx/__init__.py
dapr_httpx/dapr_api.py
dapr_httpx/error_log_helper.py
dapr_httpx/invoke_api.py
dapr_httpx/pubsub_api.py
dapr_httpx/secrets_api.py
dapr_httpx/state_api.py
dapr_httpx-0.2.6.dist-info/WHEEL
dapr_httpx-0.2.6.dist-info/METADATA
dapr_httpx-0.2.6.dist-info/RECORD
